easyxtb/__init__.py
easyxtb/calc.py
easyxtb/calculate.py
easyxtb/configuration.py
easyxtb/convert.py
easyxtb/default_config.json
easyxtb/format.py
easyxtb/geometry.py
easyxtb/parse.py
easyxtb/program.py
easyxtb-0.10.1.dist-info/METADATA
easyxtb-0.10.1.dist-info/WHEEL
easyxtb-0.10.1.dist-info/licenses/LICENSE
easyxtb-0.10.1.dist-info/RECORD
