Metadata-Version: 2.4
Name: easyxtb
Version: 0.10.1
Summary: A Python API for xtb (and CREST).
Project-URL: Homepage, https://github.com/matterhorn103/easyxtb
Project-URL: Issues, https://github.com/matterhorn103/easyxtb/issues
License-File: LICENSE
Classifier: Development Status :: 4 - Beta
Classifier: License :: OSI Approved :: BSD License
Classifier: Programming Language :: Python :: 3
Classifier: Topic :: Scientific/Engineering :: Chemistry
Requires-Python: >=3.10
Provides-Extra: docs
Requires-Dist: mkdocs-material>=9.5.49; extra == 'docs'
Requires-Dist: mkdocs>=1.6.1; extra == 'docs'
Requires-Dist: mkdocstrings[python]>=0.27.0; extra == 'docs'
